README.md
README.rst
setup.cfg
setup.py
vificov/__init__.py
vificov/__main__.py
vificov/load_config.py
vificov/vificov_main.py
vificov/vificov_utils.py
vificov.egg-info/PKG-INFO
vificov.egg-info/SOURCES.txt
vificov.egg-info/dependency_links.txt
vificov.egg-info/entry_points.txt
vificov.egg-info/requires.txt
vificov.egg-info/top_level.txt