Metadata-Version: 1.0
Name: vificov
Version: 1.0.7
Summary: Visual Field Coverage (ViFiCov) visualization in python.
Home-page: https://github.com/MSchnei/vificov
Author: Marian Schneider
Author-email: marian.schneider@maastrichtuniversity.nl
License: GNU General Public License Version 3
Keywords: pRF,fMRI,retinotopy
Platform: UNKNOWN
